hsd/__init__.py
hsd/common.py
hsd/dict.py
hsd/eventhandler.py
hsd/formatter.py
hsd/io.py
hsd/parser.py
hsd-0.1.dist-info/LICENSE
hsd-0.1.dist-info/METADATA
hsd-0.1.dist-info/WHEEL
hsd-0.1.dist-info/top_level.txt
hsd-0.1.dist-info/RECORD
