Metadata-Version: 2.1
Name: hsd
Version: 0.1
Summary: Tools for reading, writing and manipulating data stored in the human-friendly structured data (HSD) format
Home-page: https://github.com/dftbplus/hsd-python
Author: DFTB+ developers group
Author-email: info@dftbplus.org
License: BSD
Platform: any
Classifier: Intended Audience :: Developers
Classifier: License :: OSI Approved :: BSD License
Classifier: Programming Language :: Python :: 3 :: Only
Classifier: Programming Language :: Python :: 3.7
Classifier: Programming Language :: Python :: 3.8
Classifier: Programming Language :: Python :: 3.9
Classifier: Programming Language :: Python :: 3.7
License-File: LICENSE
